[{
	"number" : "002",
	"name" : "Petalen",
	"types" : ["Nature", ""],
	"abilities" : [
		{
			"name" : "Terra Growth",
			"desc" : "Increase the possessor's Nature-type moves' power to 50%."
		},
		{
			"name" : "Agility (Secret)",
			"desc" : "Increase the possessor's Speed stat by 1 stage at the end of each turn."
		}
	],
	"description" : "Petalen like to live in the forest and enjoy brushing themselves on leaves and bushes. They move swiftly between trees and their tails are used as a sharp blade that cuts down their foes and prey.",
	"gender" : {
		"male" : "50%",
		"female" : "50%"
	},
	"species" : "Cat",
	"weight" : "24.0kg",
	"height" : "1.3m",
	"stats" : {
		"hp" : "50",
		"atk" : "52",
		"def" : "51",
		"spa" : "46",
		"spd" : "37",
		"spe" : "64",
		"total" : "300"
	},
	"major_weakness" : [],
	"weakness" : ["Fire", "Ice", "Toxic"],
	"resistance" : ["Water", "Electric", "Earth" ],
	"major_resistance" : [],
	"immunity" : ["Light"],
	"moves_level" : [
		{
			"level" : "-",
			"name" : "Growl",
			"type" : "Neutral",
			"category" : "Support",
			"power" : "-",
			"accuracy" : "100%",
			"stamina" : "5",
			"effect" : "Let out a growl that lowers the opponent(s)' Attack by one stage."
		},
		{
			"level" : "-",
			"name" : "Accelerate",
			"type" : "Neutral",
			"category" : "Support",
			"power" : "-",
			"accuracy" : "-",
			"stamina" : "10",
			"effect" : "Accelerate to boost the user's Speed stat."
		},
		{
			"level" : "-",
			"name" : "Dodge",
			"type" : "Neutral",
			"category" : "Support",
			"power" : "-",
			"accuracy" : "-",
			"stamina" : "10",
			"effect" : "Dodge upcoming attack(s), but reduce success rate by 50% if used consecutively with any other evasion moves."
		},
		{
			"level" : "-",
			"name" : "Razor Leave",
			"type" : "Nature",
			"category" : "Physical",
			"power" : "50",
			"accuracy" : "90%",
			"stamina" : "15",
			"effect" : "Attack the opponent with razor sharp leaves. This move has 10% critical hit chance."
		},
		{
			"level" : "-",
			"name" : "Quick Strike",
			"type" : "Neutral",
			"category" : "Physical",
			"power" : "40",
			"accuracy" : "100%",
			"stamina" : "15",
			"effect" : "Lunges at the opponent quickly before the target can react. This move has a +1 priority."
		},
		{
			"level" : "Level 25",
			"name" : "Stalk",
			"type" : "Dark",
			"category" : "Support",
			"power" : "-",
			"accuracy" : "100%",
			"stamina" : "10",
			"effect" : "Stalk the opponent, allowing the next move to have +1 priority and 50% critical hit chance."
		},
		{
			"level" : "Level 30",
			"name" : "Copycat",
			"type" : "Neutral",
			"category" : "Other",
			"power" : "-",
			"accuracy" : "-",
			"stamina" : "15",
			"effect" : "Copy the move used immediately before the user. If no moves have been used, this move will fail."
		},
		{
			"level" : "Level 35",
			"name" : "Fury Cutter",
			"type" : "Nature",
			"category" : "Physical",
			"power" : "60",
			"accuracy" : "95%",
			"stamina" : "20",
			"effect" : "Slash the opponent with scythe-like attack. Consecutive success uses of this move increases the power by 5 each time (Max. 30)."
		},
		{
			"level" : "Level 40",
			"name" : "Shadow Claw",
			"type" : "Dark",
			"category" : "Physical",
			"power" : "60",
			"accuracy" : "100%",
			"stamina" : "15",
			"effect" : "Slash the opponent with claws made from shadow. This move has a 10% critical hit chance."
		}
	],
	"moves_tutor" : [
		{
			"name" : "Rest",
			"type" : "Neutral",
			"category" : "Support",
			"power" : "-",
			"accuracy" : "-",
			"stamina" : "10",
			"effect" : "Rest for 2 turns. Each turn restores the user's HP by 50% and Stamina by 25%. This move also removes all status condition."
		},
		{
			"name" : "Tail Slap",
			"type" : "Neutral",
			"category" : "Physical",
			"power" : "40",
			"accuracy" : "90%",
			"stamina" : "10",
			"effect" : "Slap the opponent with a tail. This move has a 20% chance of causing the target to flinch."
		},
		{
			"name" : "Photosynthesis",
			"type" : "Nature",
			"category" : "Support",
			"power" : "-",
			"accuracy" : "-",
			"stamina" : "20",
			"effect" : "Restore the user's HP by 25%. During harsh sunlight, this move restores 50% instead."
		},
		{
			"name" : "Pursuit",
			"type" : "Dark",
			"category" : "Physical",
			"power" : "40",
			"accuracy" : "75%",
			"stamina" : "10",
			"effect" : "Chase after the opponent and inflict double damage if the target switches out."
		},
		{
			"name" : "Sand Attack",
			"type" : "Earth",
			"category" : "Physical",
			"power" : "10",
			"accuracy" : "80%",
			"stamina" : "5",
			"effect" : "Hurl sand at the opponent to lower the target's Accuracy."
		}
	]
}]